{
  "name": "Depths of the Abyss",
  "shell": "shell.html",
  "css": [
    "styles/reset.css",
    "styles/hud.css",
    "styles/menus.css",
    "styles/inventory.css",
    "styles/responsive.css"
  ],
  "js": [
    "core/constants.js",
    "core/utils.js",
    "core/audio.js",
    "core/input.js",
    "core/save.js",
    "data/items.js",
    "data/enemies.js",
    "data/abilities.js",
    "data/lore.js",
    "world/tilemap.js",
    "world/dungeon-gen.js",
    "world/fog-of-war.js",
    "world/lighting.js",
    "world/camera.js",
    "combat/player.js",
    "combat/weapons.js",
    "combat/abilities.js",
    "combat/enemy-ai.js",
    "combat/boss-ai.js",
    "combat/collision.js",
    "systems/inventory.js",
    "systems/crafting.js",
    "systems/progression.js",
    "systems/particles.js",
    "systems/dialogue.js",
    "ui/title-screen.js",
    "ui/hud.js",
    "ui/menus.js",
    "ui/minimap.js",
    "ui/transitions.js",
    "core/game-loop.js"
  ],
  "output": {
    "category": "games_puzzles",
    "file": "depths-of-the-abyss.html"
  },
  "manifest": {
    "title": "Depths of the Abyss",
    "description": "Dark fantasy action RPG roguelike — 25 floors, real-time combat, skill trees, crafting, multiple endings",
    "tags": ["canvas", "rpg", "roguelike", "combat", "procedural", "audio", "particles", "boss-fights"],
    "complexity": "advanced",
    "type": "game",
    "featured": true,
    "created": "2026-02-07"
  }
}
